bunkai/__init__.py
bunkai/algorithm/__init__.py
bunkai/algorithm/bunkai_sbd/__init__.py
bunkai/algorithm/bunkai_sbd/annotator/__init__.py
bunkai/algorithm/bunkai_sbd/annotator/basic_annotator.py
bunkai/algorithm/bunkai_sbd/annotator/constant.py
bunkai/algorithm/bunkai_sbd/annotator/dot_exception_annotator.py
bunkai/algorithm/bunkai_sbd/annotator/emoji_annotator.py
bunkai/algorithm/bunkai_sbd/annotator/emotion_expression_annotator.py
bunkai/algorithm/bunkai_sbd/annotator/facemark_detector.py
bunkai/algorithm/bunkai_sbd/annotator/indirect_quote_exception_annotator.py
bunkai/algorithm/bunkai_sbd/annotator/linebreak_annotator.py
bunkai/algorithm/bunkai_sbd/annotator/linebreak_annotator_compat.py
bunkai/algorithm/bunkai_sbd/annotator/linebreak_force_annotator.py
bunkai/algorithm/bunkai_sbd/annotator/morph_annotator.py
bunkai/algorithm/bunkai_sbd/annotator/number_exception_annotator.py
bunkai/algorithm/bunkai_sbd/bunkai_sbd.py
bunkai/algorithm/lbd/__init__.py
bunkai/algorithm/lbd/corpus.py
bunkai/algorithm/lbd/custom_tokenizers.py
bunkai/algorithm/lbd/dist.py
bunkai/algorithm/lbd/predict.py
bunkai/algorithm/lbd/train.py
bunkai/algorithm/tsunoda_sbd/__init__.py
bunkai/algorithm/tsunoda_sbd/annotator/__init__.py
bunkai/algorithm/tsunoda_sbd/annotator/basic_annotator.py
bunkai/algorithm/tsunoda_sbd/annotator/constant.py
bunkai/algorithm/tsunoda_sbd/annotator/exception_no.py
bunkai/algorithm/tsunoda_sbd/annotator/exception_numeric.py
bunkai/algorithm/tsunoda_sbd/annotator/exception_particle.py
bunkai/algorithm/tsunoda_sbd/annotator/morph_annotator_janome.py
bunkai/algorithm/tsunoda_sbd/annotator/replace_parentheses.py
bunkai/algorithm/tsunoda_sbd/tsunoda_sbd.py
bunkai/base/__init__.py
bunkai/base/annotation.py
bunkai/base/annotator.py
bunkai/cli.py
bunkai/constant.py
bunkai/experiment/__init__.py
bunkai/experiment/convert/__init__.py
bunkai/experiment/convert/bccwj.py
bunkai/experiment/convert/jalan.py
bunkai/experiment/evaluate.py
bunkai/experiment/statics.py
bunkai-1.5.7.dist-info/entry_points.txt
bunkai-1.5.7.dist-info/LICENSE.txt
bunkai-1.5.7.dist-info/WHEEL
bunkai-1.5.7.dist-info/METADATA
bunkai-1.5.7.dist-info/RECORD
