Metadata-Version: 2.1
Name: bunkai
Version: 1.5.7
Summary: Sentence boundary disambiguation tool for Japanese texts
Home-page: https://github.com/megagonlabs/bunkai
License: Apache-2.0
Keywords: Japanese,Sentence boundary disambiguation
Author: Yuta Hayashibe
Author-email: hayashibe@megagon.ai
Maintainer: Yuta Hayashibe
Maintainer-email: hayashibe@megagon.ai
Requires-Python: >=3.8,<3.12
Classifier: License :: OSI Approved :: Apache Software License
Classifier: Programming Language :: Python :: 3
Classifier: Programming Language :: Python :: 3.8
Classifier: Programming Language :: Python :: 3.9
Classifier: Programming Language :: Python :: 3.10
Classifier: Programming Language :: Python :: 3.11
Provides-Extra: lb
Provides-Extra: train
Requires-Dist: dataclasses-json (>=0.5.2)
Requires-Dist: emoji (>=2.0.0)
Requires-Dist: emojis (>=0.6.0)
Requires-Dist: janome (>=0.4.1)
Requires-Dist: more_itertools (>=8.6.0)
Requires-Dist: numpy (>=1.16.0); extra == "lb"
Requires-Dist: regex (!=2022.7.24)
Requires-Dist: requests (>=2.27.1,<3.0.0); extra == "lb"
Requires-Dist: seqeval (>=1.2.2); extra == "train"
Requires-Dist: spans (>=1.1.0)
Requires-Dist: toml (>=0.10.2)
Requires-Dist: torch (>=1.3.0); extra == "lb"
Requires-Dist: tqdm
Requires-Dist: transformers (>=4.22.0); extra == "lb"
Project-URL: Repository, https://github.com/megagonlabs/bunkai
